test2_in_august/__init__.py
test2_in_august/py.typed
test2_in_august/tests/__init__.py
test2_in_august/tests/resources/.gitignore
test2_in_august/tests/resources/__init__.py
test2_in_august/tests/test_base_exception.py
test2_in_august-0.0.0.dist-info/LICENSE
test2_in_august-0.0.0.dist-info/METADATA
test2_in_august-0.0.0.dist-info/WHEEL
test2_in_august-0.0.0.dist-info/RECORD
